app_django/__init__.py
app_django/admin.py
app_django/apps.py
app_django/models.py
app_django/tests.py
app_django/urls.py
app_django/views.py
app_django/migrations/__init__.py
pack_app-0.3.2.dist-info/licenses/LICENSE
pack_app-0.3.2.dist-info/METADATA
pack_app-0.3.2.dist-info/WHEEL
pack_app-0.3.2.dist-info/entry_points.txt
pack_app-0.3.2.dist-info/top_level.txt
pack_app-0.3.2.dist-info/RECORD
